evnrg/__init__.py
evnrg/__main__.py
evnrg/bank.py
evnrg/bracket.py
evnrg/daskjob.py
evnrg/dataset.py
evnrg/datastorage.py
evnrg/eligibility.py
evnrg/evse.py
evnrg/fleet.py
evnrg/fuels.py
evnrg/intervals.py
evnrg/job_results.py
evnrg/kubejob.py
evnrg/loop.py
evnrg/numbaloop.py
evnrg/plug.py
evnrg/powertrain.py
evnrg/scenario.py
evnrg/simulation.py
evnrg/status.py
evnrg/vehicle.py
evnrg-0.1.7.post2.dist-info/AUTHORS.rst
evnrg-0.1.7.post2.dist-info/LICENSE
evnrg-0.1.7.post2.dist-info/METADATA
evnrg-0.1.7.post2.dist-info/WHEEL
evnrg-0.1.7.post2.dist-info/top_level.txt
evnrg-0.1.7.post2.dist-info/RECORD
