Metadata-Version: 2.1
Name: evnrg
Version: 0.1.7.post2
Summary: EVNRG is an EV electrical demand simulation package that takes in trip data and turns it into useful energy data given a set of assumptions.
Home-page: https://github.com/accurrently/evnrg
Author: Alex Campbell
Author-email: amcampbell@ucdavis.edu
License: Apache Software License 2.0
Keywords: evnrg
Platform: UNKNOWN
Classifier: Development Status :: 2 - Pre-Alpha
Classifier: Intended Audience :: Developers
Classifier: License :: OSI Approved :: Apache Software License
Classifier: Natural Language :: English
Classifier: Programming Language :: Python :: 3
Classifier: Programming Language :: Python :: 3.6
Classifier: Programming Language :: Python :: 3.7
Requires-Dist: numba (>=0.42.0)
Requires-Dist: numpy (>=1.16.0)
Requires-Dist: pandas (>=0.24.0)
Requires-Dist: dask
Requires-Dist: distributed
Requires-Dist: appdirs
Requires-Dist: apache-libcloud
Requires-Dist: fastparquet
Requires-Dist: pycrypto
